<annotation>
	<folder>train</folder>
	<filename>HD-wallpaper-elephant-hi-animals-arts-desert-man-smoke.jpg</filename>
	<path>C:\Users\Samya\PycharmProjects\Computer_Vision\data\images\train\HD-wallpaper-elephant-hi-animals-arts-desert-man-smoke.jpg</path>
	<source>
		<database>Unknown</database>
	</source>
	<size>
		<width>512</width>
		<height>512</height>
		<depth>3</depth>
	</size>
	<segmented>0</segmented>
	<object>
		<name>full_tusk</name>
		<pose>Unspecified</pose>
		<truncated>0</truncated>
		<difficult>0</difficult>
		<bndbox>
			<xmin>202</xmin>
			<ymin>180</ymin>
			<xmax>276</xmax>
			<ymax>294</ymax>
		</bndbox>
	</object>
	<object>
		<name>full_tusk</name>
		<pose>Unspecified</pose>
		<truncated>0</truncated>
		<difficult>0</difficult>
		<bndbox>
			<xmin>170</xmin>
			<ymin>180</ymin>
			<xmax>239</xmax>
			<ymax>302</ymax>
		</bndbox>
	</object>
</annotation>
