<annotation>
	<folder>train</folder>
	<filename>stock-photo-old-elephant-with-broken-tusk-showing-its-age-2357355619.jpg</filename>
	<path>C:\Users\Samya\PycharmProjects\Computer_Vision\data\images\train\stock-photo-old-elephant-with-broken-tusk-showing-its-age-2357355619.jpg</path>
	<source>
		<database>Unknown</database>
	</source>
	<size>
		<width>512</width>
		<height>512</height>
		<depth>3</depth>
	</size>
	<segmented>0</segmented>
	<object>
		<name>broken_tusk</name>
		<pose>Unspecified</pose>
		<truncated>0</truncated>
		<difficult>0</difficult>
		<bndbox>
			<xmin>257</xmin>
			<ymin>301</ymin>
			<xmax>274</xmax>
			<ymax>320</ymax>
		</bndbox>
	</object>
	<object>
		<name>broken_tusk</name>
		<pose>Unspecified</pose>
		<truncated>0</truncated>
		<difficult>0</difficult>
		<bndbox>
			<xmin>200</xmin>
			<ymin>301</ymin>
			<xmax>215</xmax>
			<ymax>322</ymax>
		</bndbox>
	</object>
</annotation>
